ArtexTTS/TTS.py
ArtexTTS/__init__.py
ArtexTTS/Registry/__init__.py
ArtexTTS/Registry/handle_voice.py
ArtexTTS-1.0.0.dist-info/LICENSE
ArtexTTS-1.0.0.dist-info/METADATA
ArtexTTS-1.0.0.dist-info/WHEEL
ArtexTTS-1.0.0.dist-info/top_level.txt
ArtexTTS-1.0.0.dist-info/RECORD
