Metadata-Version: 2.1
Name: ArtexTTS
Version: 1.0.0
Summary: A python text to speech library
Home-page: https://github.com/JunaidParkar/Python-TTS
Author: Artex AI
Project-URL: Documentation, https://github.com/JunaidParkar/Python-TTS
Project-URL: Source, https://github.com/JunaidParkar/Python-TTS
Project-URL: Tracker, https://github.com/JunaidParkar/Python-TTS
Classifier: Programming Language :: Python :: 3
Classifier: License :: OSI Approved :: Boost Software License 1.0 (BSL-1.0)
Classifier: Operating System :: OS Independent
Requires-Python: >=3.10
License-File: LICENSE
Requires-Dist: mtranslate==1.8
Requires-Dist: pyttsx3==2.98
